pytest_once/__init__.py
pytest_once/decorator.py
pytest_once/py.typed
pytest_once-0.1.0.dist-info/METADATA
pytest_once-0.1.0.dist-info/WHEEL
pytest_once-0.1.0.dist-info/licenses/LICENSE
pytest_once-0.1.0.dist-info/RECORD
