Metadata-Version: 2.4
Name: pytest-once
Version: 0.1.0
Summary: xdist-safe 'run once' fixture decorator for pytest (setup/teardown across workers)
Project-URL: Homepage, https://github.com/kiarina/pytest-once
Project-URL: Repository, https://github.com/kiarina/pytest-once
Project-URL: Issues, https://github.com/kiarina/pytest-once/issues
Project-URL: Changelog, https://github.com/kiarina/pytest-once/blob/main/CHANGELOG.md
Project-URL: Documentation, https://github.com/kiarina/pytest-once/tree/main#readme
Author-email: kiarina <kiarinadawa@gmail.com>
License: MIT
License-File: LICENSE
Keywords: concurrency,fixture,lock,pytest,testing,xdist
Classifier: Development Status :: 3 - Alpha
Classifier: Framework :: Pytest
Classifier: Intended Audience :: Developers
Classifier: License :: OSI Approved :: MIT License
Classifier: Operating System :: OS Independent
Classifier: Programming Language :: Python
Classifier: Programming Language :: Python :: 3
Classifier: Programming Language :: Python :: 3.12
Classifier: Programming Language :: Python :: 3.13
Classifier: Topic :: Software Development :: Testing
Requires-Python: >=3.12
Requires-Dist: filelock>=3.19.1
Requires-Dist: pytest>=8.4.0
